{"M. Montebon":{"TEAM":"AdU","MINS":25.0333333333,"2PM":1,"2PA":3,"3PM":3,"3PA":4,"FTM":4,"FTA":4,"OFF":0.0,"DEF":1.0,"AST":2.0,"TO":2.0,"STL":1.0,"BLK":0.0,"PF":3.0,"Fls on:":4.0,"+\/-":8.0,"GW":1},"J. Yerro":{"TEAM":"AdU","MINS":25.7333333333,"2PM":3,"2PA":7,"3PM":1,"3PA":3,"FTM":2,"FTA":4,"OFF":1.0,"DEF":4.0,"AST":1.0,"TO":2.0,"STL":3.0,"BLK":0.0,"PF":2.0,"Fls on:":2.0,"+\/-":5.0,"GW":1},"A. Fransman":{"TEAM":"AdU","MINS":17.7333333333,"2PM":3,"2PA":6,"3PM":0,"3PA":2,"FTM":2,"FTA":2,"OFF":0.0,"DEF":6.0,"AST":2.0,"TO":4.0,"STL":2.0,"BLK":0.0,"PF":2.0,"Fls on:":1.0,"+\/-":-2.0,"GW":1},"J. Calisay":{"TEAM":"AdU","MINS":20.0166666667,"2PM":1,"2PA":3,"3PM":1,"3PA":3,"FTM":0,"FTA":2,"OFF":1.0,"DEF":2.0,"AST":2.0,"TO":1.0,"STL":1.0,"BLK":0.0,"PF":1.0,"Fls on:":1.0,"+\/-":-5.0,"GW":1},"M. Barasi Jr":{"TEAM":"AdU","MINS":10.65,"2PM":0,"2PA":2,"3PM":0,"3PA":0,"FTM":2,"FTA":2,"OFF":1.0,"DEF":2.0,"AST":0.0,"TO":0.0,"STL":0.0,"BLK":0.0,"PF":1.0,"Fls on:":1.0,"+\/-":1.0,"GW":1},"E. Ramos":{"TEAM":"AdU","MINS":8.1,"2PM":0,"2PA":2,"3PM":0,"3PA":0,"FTM":0,"FTA":0,"OFF":1.0,"DEF":2.0,"AST":0.0,"TO":1.0,"STL":0.0,"BLK":0.0,"PF":2.0,"Fls on:":1.0,"+\/-":-11.0,"GW":1},"C. Alexander":{"TEAM":"AdU","MINS":3.45,"2PM":0,"2PA":0,"3PM":0,"3PA":0,"FTM":0,"FTA":0,"OFF":0.0,"DEF":1.0,"AST":0.0,"TO":0.0,"STL":0.0,"BLK":0.0,"PF":1.0,"Fls on:":0.0,"+\/-":-1.0,"GW":1},"A. Ignacio":{"TEAM":"AdU","MINS":1.4,"2PM":0,"2PA":0,"3PM":0,"3PA":0,"FTM":0,"FTA":0,"OFF":1.0,"DEF":0.0,"AST":0.0,"TO":0.0,"STL":0.0,"BLK":0.0,"PF":0.0,"Fls on:":0.0,"+\/-":0.0,"GW":1},"M. Erolon":{"TEAM":"AdU","MINS":12.3333333333,"2PM":1,"2PA":3,"3PM":1,"3PA":1,"FTM":0,"FTA":0,"OFF":0.0,"DEF":0.0,"AST":3.0,"TO":1.0,"STL":2.0,"BLK":0.0,"PF":3.0,"Fls on:":0.0,"+\/-":-1.0,"GW":1},"C. Manzano":{"TEAM":"AdU","MINS":15.9666666667,"2PM":2,"2PA":7,"3PM":0,"3PA":0,"FTM":1,"FTA":2,"OFF":5.0,"DEF":2.0,"AST":1.0,"TO":3.0,"STL":0.0,"BLK":1.0,"PF":4.0,"Fls on:":5.0,"+\/-":10.0,"GW":1},"M. Ojarikre":{"TEAM":"AdU","MINS":24.15,"2PM":1,"2PA":2,"3PM":0,"3PA":0,"FTM":2,"FTA":7,"OFF":5.0,"DEF":12.0,"AST":0.0,"TO":2.0,"STL":0.0,"BLK":1.0,"PF":1.0,"Fls on:":4.0,"+\/-":-1.0,"GW":1},"M. Anabo":{"TEAM":"AdU","MINS":21.8166666667,"2PM":0,"2PA":0,"3PM":1,"3PA":7,"FTM":0,"FTA":0,"OFF":0.0,"DEF":4.0,"AST":1.0,"TO":0.0,"STL":0.0,"BLK":0.0,"PF":3.0,"Fls on:":2.0,"+\/-":8.0,"GW":1},"R. Mantua":{"TEAM":"AdU","MINS":13.5166666667,"2PM":1,"2PA":3,"3PM":0,"3PA":1,"FTM":0,"FTA":0,"OFF":0.0,"DEF":0.0,"AST":2.0,"TO":1.0,"STL":0.0,"BLK":0.0,"PF":1.0,"Fls on:":1.0,"+\/-":-1.0,"GW":1},"I. Manansala":{"TEAM":"NU","MINS":20.3833333333,"2PM":4,"2PA":7,"3PM":0,"3PA":1,"FTM":7,"FTA":9,"OFF":5.0,"DEF":4.0,"AST":2.0,"TO":0.0,"STL":0.0,"BLK":0.0,"PF":3.0,"Fls on:":6.0,"+\/-":16.0,"GW":0},"P. Palacielo":{"TEAM":"NU","MINS":23.85,"2PM":4,"2PA":12,"3PM":0,"3PA":0,"FTM":0,"FTA":0,"OFF":2.0,"DEF":4.0,"AST":1.0,"TO":1.0,"STL":0.0,"BLK":1.0,"PF":3.0,"Fls on:":0.0,"+\/-":-1.0,"GW":0},"R. Jumamoy":{"TEAM":"NU","MINS":13.3166666667,"2PM":0,"2PA":6,"3PM":1,"3PA":3,"FTM":2,"FTA":2,"OFF":0.0,"DEF":1.0,"AST":1.0,"TO":2.0,"STL":4.0,"BLK":0.0,"PF":1.0,"Fls on:":2.0,"+\/-":6.0,"GW":0},"S. Enriquez":{"TEAM":"NU","MINS":16.4,"2PM":1,"2PA":3,"3PM":0,"3PA":1,"FTM":2,"FTA":2,"OFF":0.0,"DEF":2.0,"AST":1.0,"TO":3.0,"STL":0.0,"BLK":0.0,"PF":0.0,"Fls on:":2.0,"+\/-":-1.0,"GW":0},"P. Francisco":{"TEAM":"NU","MINS":14.2833333333,"2PM":1,"2PA":2,"3PM":0,"3PA":1,"FTM":0,"FTA":0,"OFF":1.0,"DEF":0.0,"AST":1.0,"TO":1.0,"STL":2.0,"BLK":0.0,"PF":2.0,"Fls on:":1.0,"+\/-":-1.0,"GW":0},"P. Yu":{"TEAM":"NU","MINS":19.2333333333,"2PM":0,"2PA":0,"3PM":0,"3PA":2,"FTM":0,"FTA":0,"OFF":3.0,"DEF":1.0,"AST":2.0,"TO":0.0,"STL":0.0,"BLK":0.0,"PF":2.0,"Fls on:":0.0,"+\/-":8.0,"GW":0},"B. Parks":{"TEAM":"NU","MINS":1.7833333333,"2PM":0,"2PA":0,"3PM":0,"3PA":0,"FTM":0,"FTA":0,"OFF":0.0,"DEF":1.0,"AST":1.0,"TO":0.0,"STL":0.0,"BLK":0.0,"PF":0.0,"Fls on:":0.0,"+\/-":-2.0,"GW":0},"D. Lim":{"TEAM":"NU","MINS":8.3666666667,"2PM":0,"2PA":1,"3PM":0,"3PA":0,"FTM":0,"FTA":0,"OFF":0.0,"DEF":1.0,"AST":0.0,"TO":0.0,"STL":0.0,"BLK":0.0,"PF":0.0,"Fls on:":0.0,"+\/-":-1.0,"GW":0},"N. Tulabut":{"TEAM":"NU","MINS":3.6166666667,"2PM":0,"2PA":1,"3PM":0,"3PA":1,"FTM":0,"FTA":0,"OFF":0.0,"DEF":1.0,"AST":0.0,"TO":0.0,"STL":0.0,"BLK":0.0,"PF":0.0,"Fls on:":0.0,"+\/-":-6.0,"GW":0},"E. Dela Cruz":{"TEAM":"NU","MINS":1.7166666667,"2PM":0,"2PA":0,"3PM":0,"3PA":0,"FTM":0,"FTA":0,"OFF":0.0,"DEF":0.0,"AST":0.0,"TO":0.0,"STL":0.0,"BLK":0.0,"PF":0.0,"Fls on:":0.0,"+\/-":-4.0,"GW":0},"J. Figueroa":{"TEAM":"NU","MINS":29.1,"2PM":3,"2PA":11,"3PM":0,"3PA":3,"FTM":5,"FTA":7,"OFF":2.0,"DEF":4.0,"AST":1.0,"TO":1.0,"STL":1.0,"BLK":0.0,"PF":4.0,"Fls on:":5.0,"+\/-":-1.0,"GW":0},"K. Padrones":{"TEAM":"NU","MINS":21.2,"2PM":4,"2PA":6,"3PM":0,"3PA":0,"FTM":2,"FTA":2,"OFF":2.0,"DEF":4.0,"AST":0.0,"TO":1.0,"STL":0.0,"BLK":0.0,"PF":1.0,"Fls on:":4.0,"+\/-":-3.0,"GW":0},"G. Santiago":{"TEAM":"NU","MINS":12.1,"2PM":0,"2PA":2,"3PM":1,"3PA":5,"FTM":0,"FTA":0,"OFF":2.0,"DEF":3.0,"AST":0.0,"TO":0.0,"STL":0.0,"BLK":0.0,"PF":2.0,"Fls on:":3.0,"+\/-":-10.0,"GW":0},"T. Garcia":{"TEAM":"NU","MINS":10.5166666667,"2PM":0,"2PA":2,"3PM":0,"3PA":0,"FTM":0,"FTA":0,"OFF":0.0,"DEF":1.0,"AST":2.0,"TO":3.0,"STL":0.0,"BLK":0.0,"PF":3.0,"Fls on:":0.0,"+\/-":-8.0,"GW":0},"K. Perciano":{"TEAM":"NU","MINS":4.0166666667,"2PM":0,"2PA":0,"3PM":0,"3PA":0,"FTM":0,"FTA":0,"OFF":0.0,"DEF":1.0,"AST":0.0,"TO":1.0,"STL":0.0,"BLK":0.0,"PF":1.0,"Fls on:":0.0,"+\/-":-2.0,"GW":0}}